hpsearch/__init__.py
hpsearch/_nbdev.py
hpsearch/experiment_manager.py
hpsearch/app_config/__init__.py
hpsearch/app_config/subclassed_manager.py
hpsearch/app_config/subclassed_manager_import.py
hpsearch/config/__init__.py
hpsearch/config/hp_defaults.py
hpsearch/config/hpconfig.py
hpsearch/config/manager_factory.py
hpsearch/examples/__init__.py
hpsearch/examples/complex_dummy_experiment_manager.py
hpsearch/examples/dummy_experiment_manager.py
hpsearch/examples/example_experiment.py
hpsearch/examples/example_experiment_manager.py
hpsearch/tools/__init__.py
hpsearch/tools/change_manager.py
hpsearch/tools/copy_experiment.py
hpsearch/tools/metric_visualization.py
hpsearch/tools/modify_manager.py
hpsearch/tools/more_runs.py
hpsearch/tools/print_info.py
hpsearch/tools/print_parameters.py
hpsearch/tools/print_table.py
hpsearch/tools/query.py
hpsearch/tools/remove_experiments.py
hpsearch/tools/rerun.py
hpsearch/tools/utils.py
hpsearch/utils/__init__.py
hpsearch/utils/convert_legacy.py
hpsearch/utils/experiment_utils.py
hpsearch/utils/organize_experiments.py
hpsearch/visualization/__init__.py
hpsearch/visualization/experiment_visualization.py
hpsearch/visualization/plot_utils.py
tests/__init__.py
tests/test_experiment_manager.py
tests/config/__init__.py
tests/config/test_hpconfig.py
tests/config/test_manager_factory.py
tests/examples/__init__.py
tests/examples/test_complex_dummy_experiment_manager.py
tests/examples/test_dummy_experiment_manager.py
tests/examples/test_example_experiment_manager.py
tests/tools/__init__.py
tests/tools/test_change_manager.py
tests/tools/test_copy_experiment.py
tests/tools/test_metric_visualization.py
tests/tools/test_modify_manager.py
tests/tools/test_more_runs.py
tests/tools/test_print_info.py
tests/tools/test_print_parameters.py
tests/tools/test_print_table.py
tests/tools/test_query.py
tests/tools/test_remove_experiments.py
tests/tools/test_rerun.py
tests/utils/__init__.py
tests/utils/test_convert_legacy.py
tests/utils/test_experiment_utils.py
hpsearch-0.0.7.dist-info/LICENSE
hpsearch-0.0.7.dist-info/METADATA
hpsearch-0.0.7.dist-info/WHEEL
hpsearch-0.0.7.dist-info/entry_points.txt
hpsearch-0.0.7.dist-info/top_level.txt
hpsearch-0.0.7.dist-info/RECORD
