Metadata-Version: 2.1
Name: hpsearch
Version: 0.0.7
Summary: A description of your project
Home-page: https://github.com/Jaume-JCI/hpsearch/tree/master/
Author: Jaume Amores
Author-email: jamorej@jci.com
License: MIT License
Keywords: some keywords
Classifier: Development Status :: 3 - Alpha
Classifier: Intended Audience :: Developers
Classifier: License :: OSI Approved :: MIT License
Classifier: Natural Language :: English
Classifier: Programming Language :: Python :: 3.6
Classifier: Programming Language :: Python :: 3.7
Classifier: Programming Language :: Python :: 3.8
Requires-Python: >=3.6
License-File: LICENSE
Requires-Dist: pip
Requires-Dist: packaging
Requires-Dist: pandas
Requires-Dist: numpy
Requires-Dist: scikit-learn
Requires-Dist: scikit-optimize
Requires-Dist: optuna
Requires-Dist: cloudpickle
Requires-Dist: dill
Requires-Dist: plotly
Requires-Dist: visdom
Requires-Dist: matplotlib
Provides-Extra: dev
